MANIFEST.in
README.md
requirements.txt
setup.py
pyicloud/__init__.py
pyicloud/base.py
pyicloud/exceptions.py
pyicloud/services/__init__.py
pyicloud/services/calendar.py
pyicloud/services/contacts.py
pyicloud/services/findmyiphone.py
pyicloud/services/ubiquity.py
pyicloud_dwoh.egg-info/PKG-INFO
pyicloud_dwoh.egg-info/SOURCES.txt
pyicloud_dwoh.egg-info/dependency_links.txt
pyicloud_dwoh.egg-info/requires.txt
pyicloud_dwoh.egg-info/top_level.txt