Metadata-Version: 1.0
Name: pyicloud-dwoh
Version: 0.4
Summary: PyiCloud is a module which allows pythonistas to interact with iCloud webservices.  This is an unofficial fork of the official package 'pyicloud'.
Home-page: https://github.com/latestrevision/pyicloud
Author: Peter Evans and Adam Coddington
Author-email: me@adamcoddington.net
License: UNKNOWN
Platform: UNKNOWN
